llmfunctionclient/__init__.py
llmfunctionclient/main.py
llmfunctionclient-0.1.5.dist-info/LICENSE.md
llmfunctionclient-0.1.5.dist-info/METADATA
llmfunctionclient-0.1.5.dist-info/WHEEL
llmfunctionclient-0.1.5.dist-info/RECORD
